samtecdeviceshare/__init__.py
samtecdeviceshare/aiofilelock.py
samtecdeviceshare/balena/__init__.py
samtecdeviceshare/balena/api.py
samtecdeviceshare/emulation/__init__.py
samtecdeviceshare/emulation/networkmanager.py
samtecdeviceshare/fastapi_utils.py
samtecdeviceshare/helper.py
samtecdeviceshare/logger.py
samtecdeviceshare/nm_utils.py
samtecdeviceshare/sdshare.py
samtecdeviceshare/server.py
samtecdeviceshare/types.py
samtecdeviceshare/wiredhandler.py
samtecdeviceshare-2.9.1.dist-info/LICENSE.md
samtecdeviceshare-2.9.1.dist-info/METADATA
samtecdeviceshare-2.9.1.dist-info/WHEEL
samtecdeviceshare-2.9.1.dist-info/RECORD
