Metadata-Version: 2.1
Name: samtecdeviceshare
Version: 2.9.1
Summary: Handles a variety of common routines for SDC-based applications
License: MIT
Author: Adam Page
Author-email: adam.page@samtec.com
Requires-Python: >=3.8,<4.0
Classifier: License :: OSI Approved :: MIT License
Classifier: Programming Language :: Python :: 3
Classifier: Programming Language :: Python :: 3.8
Classifier: Programming Language :: Python :: 3.9
Classifier: Programming Language :: Python :: 3.10
Classifier: Programming Language :: Python :: 3.11
Requires-Dist: PyYAML (>=6.0.1,<7.0.0)
Requires-Dist: aiofiles (>=0.6.0,<0.7.0)
Requires-Dist: dbus-python ; sys_platform == "linux"
Requires-Dist: fastapi (>=0.63.0,<0.64.0)
Requires-Dist: httpx (>=0.16.1,<0.17.0)
Requires-Dist: pyaml-env (>=1.1.0,<2.0.0)
Requires-Dist: pydantic (>=1.7.3,<2.0.0)
Requires-Dist: pyhumps (>=1.6.1,<2.0.0)
Requires-Dist: python-networkmanager ; sys_platform == "linux"
Requires-Dist: uvicorn (>=0.13.3,<0.14.0)
